README.rst
setup.py
stashy/__init__.py
stashy/client.py
stashy/compat.py
stashy/errors.py
stashy/helpers.py
stashy/permissions.py
stashy/projects.py
stashy/pullrequests.py
stashy/repos.py
stashy/admin/__init__.py
stashy/admin/groups.py
stashy/admin/users.py
stashyEvry.egg-info/PKG-INFO
stashyEvry.egg-info/SOURCES.txt
stashyEvry.egg-info/dependency_links.txt
stashyEvry.egg-info/requires.txt
stashyEvry.egg-info/top_level.txt