Metadata-Version: 1.0
Name: stashyEvry
Version: 0.1a1dev0
Summary: Python API client for the Atlassian Stash REST API
Home-page: http://github.com/RisingOak/stashy
Author: Cosmin Stejerean
Author-email: cosmin@offbytwo.com
License: Apache License 2.0
Download-URL: https://github.com/RisingOak/stashy/tarball/0.1
Platform: UNKNOWN
Classifier: Development Status :: 3 - Alpha
Classifier: License :: OSI Approved :: Apache Software License
Classifier: Topic :: Software Development :: Libraries
